{"article_id": "103548", "revised_title": "A Description of the Oxyoides Plant and its Sensitivity to Touch", "semantic_tags": ["Botany", "Plant Physiology", "Plant Sensitivity", "Oxyoides", "Tamarind"], "scientific_discipline": "Biology and Life Sciences > Botany", "tldr": "The author describes a new family of plants called Oxyoides, which are similar to Tamarind leaves in appearance and have a high sensitivity to touch. The Oxyoides plant grows in the Island of Java and possibly other islands in the region. The leaves close when touched and open again gradually, and they also respond to sunlight and moisture in their environment."}