{"article_id": "104365", "revised_title": "Surgical Treatment of Thigh Bone Infection and Healing", "semantic_tags": ["Orthopedic Surgery", "Bone Infections", "Wound Healing", "Tissue Regeneration", "Case Study"], "tldr": "This article presents a case study of a young man with a large piece of thigh bone removed due to infection and replaced by a callus. The patient was treated by a surgeon who used a combination of surgical techniques and medications to heal the wound and restore the patient's mobility. The case highlights the importance of proper wound care and the body's ability to regenerate tissue.", "scientific_discipline": "Medicine and Health Sciences > Orthopedic Surgery"}