{"article_id": "104310", "revised_title": "Investigating Ancient Barrows in Cornwall", "semantic_tags": ["Archaeology", "Cornish history", "Burial mounds", "Stone structures", "Ancient cultures"], "tldr": "The author examines ancient barrows in Cornwall, studying their construction, contents, and the materials used. They find that these structures were built by different nations and cultures, and often contained urns with burnt bones and ashes. The author also discusses the possible purposes of these barrows and their significance in the history of Cornwall.", "scientific_discipline": "Social Sciences, Art, and Humanities > Archaeology"}