{"article_id": "106555", "revised_title": "Election Procedures of the Royal Society", "semantic_tags": ["Governance", "Election process", "Scientific organizations", "Council selection", "Officer election"], "tldr": "This article outlines the election process for the Royal Society's Council and Officers. It details the procedures for selecting members of the Council, as well as the President, Treasurer, and Secretaries. The article emphasizes the importance of attendance and participation in the election process for the good of the Society.", "scientific_discipline": "Social Sciences, Art, and Humanities > Governance"}