{"article_id": "110043", "revised_title": "Temperature Variations in the Caribbean Sea Depths", "semantic_tags": ["Oceanography", "Temperature measurement", "Thermometer", "Caribbean Sea", "Deep-sea exploration"], "tldr": "In a letter to Sir Humphry Davy, Edward Sabine reports the temperature at considerable depths in the Caribbean Sea. At a depth of 1230 fathoms, a thermometer indicated a temperature of 450\u00b0F, while the surface water temperature varied from 820\u00b0F to 830\u00b0F. This difference amounted to 37\u00b0F.", "scientific_discipline": "Environmental and Earth Sciences > Oceanography"}