{"article_id": "rsbm_1984_0019", "revised_title": "Alfred Spinks: A Pioneering Chemist and His Life", "semantic_tags": ["Chemistry", "Biographies", "Vitamin A synthesis", "Pharmaceutical chemistry", "ICI"], "tldr": "The article is a biography of Alfred Spinks, a prominent chemist who made significant contributions to the synthesis of vitamin A. Born in Littleport, England, Spinks showed exceptional talent in chemistry from a young age. He attended Nottingham University College, where he earned a B.Sc. in Chemistry with first-class honors. Later, he worked at Imperial College, London, where he synthesized vitamin A and made other important discoveries in pharmaceutical chemistry. Spinks eventually joined ICI, where he worked on therapeutic agents and made a lasting impact in the field of chemistry.", "scientific_discipline": "Chemistry > Pharmaceutical chemistry"}