{"article_id": "rsnr_1958_0014", "revised_title": "Boyle and Harvey: A Personal Connection and Its Impact on Science", "semantic_tags": ["History of Science", "William Harvey", "Robert Boyle", "Medical History", "Scientific Collaboration"], "tldr": "This article explores the personal connection between William Harvey and Robert Boyle, two prominent figures in the history of science. It examines their interactions, shared interests, and the impact of their collaboration on the development of scientific knowledge. The authors highlight the importance of their relationship in shaping the scientific community and advancing our understanding of the human body and natural phenomena.", "scientific_discipline": "Social Sciences, Art, and Humanities > History of Science"}