{"article_id": "rsnr_1938_0022", "revised_title": "The Bermuda Oceanographical Committee and Its Research Vessel", "semantic_tags": ["Oceanography", "Bermuda Biological Station", "Gulf Stream", "Research Vessel", "Hydrography"], "tldr": "The Royal Society took responsibility for the Bermuda Oceanographical Committee, which aimed to develop oceanographic research based on the Bermuda Biological Station. They acquired a research vessel, the Culver, to conduct hydrographic observations and study the Gulf Stream's fluctuations. The committee also strengthened the Bermuda Biological Station's resources and added more scientific staff to support the research.", "scientific_discipline": "Environmental and Earth Sciences > Oceanography"}