{"article_id": "rspa_1926_0165", "revised_title": "Pressure and Gas Conductivity Effects on Heat Conduction through Powders", "semantic_tags": ["Heat conduction", "Powder insulation", "Gas conductivity", "Thermal insulation", "Pressure effects"], "tldr": "The authors investigated the conduction of heat through powders and found that the conductivity of the powder is linearly related to the logarithm of the pressure of the gas in which it is immersed. This relationship is important for understanding the thermal insulation properties of powders, cellular, and fibrous substances.", "scientific_discipline": "Physics > Thermodynamics"}