{"article_id": "rspa_1960_0144", "revised_title": "Monotone Networks and Their Applications", "semantic_tags": ["Graph Theory", "Optimization", "Network Theory", "Mathematics", "Electrical Engineering"], "tldr": "The article discusses monotone networks, which are networks with resistors that have a specific property called \"monotonicity.\" The authors explore the mathematical properties of these networks and their applications in electrical engineering, particularly in finding solutions to minimize functions and maximize efficiency in circuits.", "scientific_discipline": "Mathematics > Graph Theory"}