{"article_id": "rspb_1966_0023", "revised_title": "Identifying Cistrons in Higher Organisms: The Rosy Locus in Drosophila Melanogaster", "semantic_tags": ["Genetics", "Cistrons", "Gene organization", "Drosophila melanogaster", "Enzyme activity"], "scientific_discipline": "Biology and Life Sciences > Genetics", "tldr": "The author investigates the genetic organization in higher organisms, focusing on the rosy locus in Drosophila melanogaster. They identify a single cistron responsible for xanthine dehydrogenase enzyme activity and eye pigment production. The study provides insights into understanding gene organization and function in higher organisms, using the microbial model as a reference."}