{"article_id": "rspb_1950_0050", "revised_title": "The Evolution and Impact of Industrial Research Laboratories", "semantic_tags": ["Industrial Research", "Technology Development", "Organizational Structure", "Applied Science", "Innovation"], "tldr": "The author discusses the evolution and importance of industrial research laboratories, using the Bell Telephone Laboratories as an example. These laboratories integrate research, development, design, and engineering to create new products and facilities. The author highlights the unique organizational structure of the Bell System, which is responsible for its own technology and manufacturing, and its impact on the advancement of telecommunications.", "scientific_discipline": "Social Sciences, Art, and Humanities > Organizational Studies"}