{"article_id": "rspl_1893_0087", "revised_title": "Royal Society's 1893 Anniversary Meeting and Newton's Principia Mathematica", "semantic_tags": ["History of Science", "Royal Society", "Isaac Newton", "Principia Mathematica", "Scientific Publishing"], "tldr": "The 1893 Anniversary Meeting of the Royal Society discussed the Society's activities, losses of members, and the history of Isaac Newton's publication of 'Philosophi\u00e6 Naturalis Principia Mathematica.' The Society's Council considered printing the book at the expense of Edmond Halley, who took on the task of editing and publishing the work. The meeting highlighted the importance of scientific publications and the challenges faced in their production.", "scientific_discipline": "Social Sciences, Art, and Humanities > History of Science"}