{"article_id": "rstb_1889_0009", "revised_title": "Erratum: Researches on the Structure, Organisation, and Classification of the Fossil Reptilia", "semantic_tags": ["Paleontology", "Reptiles", "Saliva secretion", "Cardium edule", "Nitrogen sources", "Electromotive changes"], "scientific_discipline": "Biology and Life Sciences > Paleontology", "tldr": "This article is an erratum for the research on the structure, organization, and classification of fossil reptiles. It also discusses variations in Cardium edule, the sources of nitrogen in vegetation, and electromotive changes related to the mammalian and human heart."}