{"article_id": "rstb_1995_0104", "revised_title": "The Dangers of Anthropomorphism in Science", "semantic_tags": ["Anthropomorphism", "Scientific Language", "Evolutionary Theory", "Biology", "Dawkins' Theory"], "tldr": "The author argues that the use of anthropomorphic language in scientific explanations can lead to misleading interpretations and pseudo-theories. She provides examples from recent biological research, such as the work of Dawkins and Hurst, where the language of conflict and selfishness has replaced the objective descriptions of natural selection. The author emphasizes the importance of maintaining scientific purity by avoiding anthropomorphic language and promoting clear, objective descriptions of biological phenomena.", "scientific_discipline": "Biology > Evolutionary Theory"}